djangocms_pai_contact/__init__.py
djangocms_pai_contact/admin.py
djangocms_pai_contact/apps.py
djangocms_pai_contact/models.py
djangocms_pai_contact/serializers.py
djangocms_pai_contact/tests.py
djangocms_pai_contact/urls.py
djangocms_pai_contact/views.py
djangocms_pai_contact/migrations/0001_initial.py
djangocms_pai_contact/migrations/__init__.py
djangocms_pai_contact-0.0.1.dist-info/AUTHORS.rst
djangocms_pai_contact-0.0.1.dist-info/LICENSE.txt
djangocms_pai_contact-0.0.1.dist-info/METADATA
djangocms_pai_contact-0.0.1.dist-info/WHEEL
djangocms_pai_contact-0.0.1.dist-info/top_level.txt
djangocms_pai_contact-0.0.1.dist-info/RECORD
